RaceData/RaceData.py
RaceData/__init__.py
RaceDatam-0.0.1.dist-info/METADATA
RaceDatam-0.0.1.dist-info/WHEEL
RaceDatam-0.0.1.dist-info/top_level.txt
RaceDatam-0.0.1.dist-info/RECORD
